napalm_sros/__init__.py
napalm_sros/nc_filters.py
napalm_sros/sros.py
napalm_sros/api/__init__.py
napalm_sros/api/get_bgp_neighbors.py
napalm_sros/api/get_bgp_neighbors_detail.py
napalm_sros/api/util.py
napalm_sros/templates/__init__.py
napalm_sros/templates/set_hostname.j2
napalm_sros/utils/__init__.py
napalm_sros/utils/parse_output_to_dict.py
napalm_sros/utils/textfsm_templates/__init__.py
napalm_sros/utils/textfsm_templates/nokia_sros_show_service_fdb_mac.tpl
napalm_sros-1.0.2.dist-info/AUTHORS
napalm_sros-1.0.2.dist-info/LICENSE
napalm_sros-1.0.2.dist-info/METADATA
napalm_sros-1.0.2.dist-info/WHEEL
napalm_sros-1.0.2.dist-info/top_level.txt
napalm_sros-1.0.2.dist-info/RECORD
