Metadata-Version: 2.1
Name: napalm-sros
Version: 1.0.2
Summary: Network Automation and Programmability Abstraction Layer driver for Nokia SR OS
Home-page: https://github.com/napalm-automation/napalm-sros
Author: Nokia
Author-email: Ashna Shah <ashna.shah@nokia.com>, Roman Dodin <roman.dodin@nokia.com>, Patryk Szulczewski <patryk.szulczewski@nokia.com>, Jeroen van Bemmel <jeroen.van_bemmel@nokia.com>
Project-URL: Homepage, https://github.com/napalm-automation-community/napalm-sros
Project-URL: Bug Tracker, https://github.com/napalm-automation-community/napalm-sros/issues
Classifier: Topic :: System :: Networking
Classifier: Programming Language :: Python :: 3
Classifier: Programming Language :: Python :: 3.8
Classifier: Programming Language :: Python :: 3.9
Classifier: Programming Language :: Python :: 3.10
Classifier: Programming Language :: Python :: 3.11
Classifier: Programming Language :: Python :: 3.12
Classifier: Natural Language :: English
Requires-Python: >=3.7
License-File: LICENSE
License-File: AUTHORS
Requires-Dist: napalm >=4.0.0
Requires-Dist: pytest >=7.0.1
Requires-Dist: setuptools >=47.3.1
Requires-Dist: pip >=21.3.1
Requires-Dist: textfsm
Requires-Dist: paramiko >=2.11.0
Requires-Dist: lxml >=4.9.1
Requires-Dist: ncclient >=0.6.15
Requires-Dist: xmltodict >=0.12.0
Requires-Dist: dictdiffer >=0.9.0
Requires-Dist: datetime >=4.7
Provides-Extra: tests
Requires-Dist: pytest ; extra == 'tests'
Requires-Dist: ruff ; extra == 'tests'
